LICENSE
LICENSE_fourcastnet
README.md
pyproject.toml
setup.py
ai_models_fourcastnet/__init__.py
ai_models_fourcastnet/afnonet.py
ai_models_fourcastnet/model.py
ai_models_fourcastnet.egg-info/PKG-INFO
ai_models_fourcastnet.egg-info/SOURCES.txt
ai_models_fourcastnet.egg-info/dependency_links.txt
ai_models_fourcastnet.egg-info/entry_points.txt
ai_models_fourcastnet.egg-info/requires.txt
ai_models_fourcastnet.egg-info/top_level.txt
ai_models_fourcastnet.egg-info/zip-safe